{
  "network": "zgTestnetV4",
  "chainId": "16602",
  "timestamp": "2026-01-22T06:46:51.551Z",
  "contractName": "InferenceServing_v1.0",
  "artifact": "InferenceServing",
  "newImplementation": "0x4EBB1e1F179A616cd098f85Edd3697f1F516013B",
  "beacon": "0xa543f577aB2c3e4A103dd6F947E70a83eC436d78",
  "currentImplementation": "0xe6543f5C1d56da0a0E31f1DF651623994f6F3730",
  "action": {
    "method": "upgradeTo(address)",
    "methodSignature": "0x3659cfe6",
    "parameter": "0x4EBB1e1F179A616cd098f85Edd3697f1F516013B"
  },
  "instructions": [
    "1. Open beacon contract on chain explorer: 0xa543f577aB2c3e4A103dd6F947E70a83eC436d78",
    "2. Navigate to \"Write Contract\" or \"Write as Proxy\" tab",
    "3. Connect Foundation wallet (must be beacon owner)",
    "4. Find and call upgradeTo(address) method",
    "5. Input new implementation address: 0x4EBB1e1F179A616cd098f85Edd3697f1F516013B",
    "6. Confirm and submit transaction",
    "7. Verify upgrade by calling implementation() - should return: 0x4EBB1e1F179A616cd098f85Edd3697f1F516013B"
  ]
}